clangd_tidy/__init__.py
clangd_tidy/__main__.py
clangd_tidy/_dist_ver.py
clangd_tidy/args.py
clangd_tidy/clangd_tidy_diff_cli.py
clangd_tidy/diagnostic_formatter.py
clangd_tidy/line_filter.py
clangd_tidy/main_cli.py
clangd_tidy/version.py
clangd_tidy/lsp/__init__.py
clangd_tidy/lsp/clangd.py
clangd_tidy/lsp/client.py
clangd_tidy/lsp/messages.py
clangd_tidy/lsp/rpc.py
clangd_tidy/lsp/server.py
clangd_tidy-1.1.0.post2.dist-info/LICENSE
clangd_tidy-1.1.0.post2.dist-info/METADATA
clangd_tidy-1.1.0.post2.dist-info/WHEEL
clangd_tidy-1.1.0.post2.dist-info/entry_points.txt
clangd_tidy-1.1.0.post2.dist-info/top_level.txt
clangd_tidy-1.1.0.post2.dist-info/RECORD
