Metadata-Version: 2.1
Name: clangd-tidy
Version: 1.1.0.post2
Summary: A faster alternative to clang-tidy
Author-email: lljbash <lljbash@gmail.com>
Project-URL: Homepage, https://github.com/lljbash/clangd-tidy
Project-URL: Bug Tracker, https://github.com/lljbash/clangd-tidy/issues
Keywords: clang-tidy,clangd,static-analysis,cpp
Classifier: Development Status :: 4 - Beta
Classifier: Environment :: Console
Classifier: Intended Audience :: Developers
Classifier: License :: OSI Approved :: MIT License
Classifier: Operating System :: POSIX
Classifier: Programming Language :: Python :: 3 :: Only
Classifier: Topic :: Software Development :: Quality Assurance
Requires-Python: >=3.8
License-File: LICENSE
Requires-Dist: attrs
Requires-Dist: cattrs
Requires-Dist: typing-extensions
